saki/__init__.py
saki/__main__.py
saki/info.py
saki/main.py
saki-1.1.3.dist-info/entry_points.txt
saki-1.1.3.dist-info/WHEEL
saki-1.1.3.dist-info/METADATA
saki-1.1.3.dist-info/RECORD
